<annotation>
		<filename>0248.jpg</filename>
		<object>
			<name>without_helmet</name>
			<ID>0</ID>
			<bndbox>
				<xmin>1266</xmin>
				<ymin>726</ymin>
				<xmax>1367</xmax>
				<ymax>853</ymax>
			</bndbox>
		</object>
		<object>
			<name>without_helmet</name>
			<ID>0</ID>
			<bndbox>
				<xmin>1139</xmin>
				<ymin>729</ymin>
				<xmax>1248</xmax>
				<ymax>840</ymax>
			</bndbox>
		</object>
		<object>
			<name>without_helmet</name>
			<bndbox>
				<xmin>352</xmin>
				<ymin>490</ymin>
				<xmax>377</xmax>
				<ymax>514</ymax>
			</bndbox>
		</object>
		<object>
			<name>helmet</name>
			<bndbox>
				<xmin>556</xmin>
				<ymin>534</ymin>
				<xmax>584</xmax>
				<ymax>560</ymax>
			</bndbox>
		</object>
		<object>
			<name>two_wheeler</name>
			<ID>0</ID>
			<bndbox>
				<xmin>1053</xmin>
				<ymin>717</ymin>
				<xmax>1589</xmax>
				<ymax>1080</ymax>
			</bndbox>
		</object>
	</annotation>