<annotation>
		<filename>0335.jpg</filename>
		<object>
			<name>helmet</name>
			<ID>0</ID>
			<bndbox>
				<xmin>521</xmin>
				<ymin>558</ymin>
				<xmax>572</xmax>
				<ymax>617</ymax>
			</bndbox>
		</object>
		<object>
			<name>without_helmet</name>
			<ID>1</ID>
			<bndbox>
				<xmin>297</xmin>
				<ymin>589</ymin>
				<xmax>361</xmax>
				<ymax>649</ymax>
			</bndbox>
		</object>
		<object>
			<name>two_wheeler</name>
			<ID>0</ID>
			<bndbox>
				<xmin>478</xmin>
				<ymin>552</ymin>
				<xmax>688</xmax>
				<ymax>874</ymax>
			</bndbox>
		</object>
		<object>
			<name>two_wheeler</name>
			<ID>1</ID>
			<bndbox>
				<xmin>254</xmin>
				<ymin>600</ymin>
				<xmax>441</xmax>
				<ymax>924</ymax>
			</bndbox>
		</object>
	</annotation>