<annotation>
		<filename>0860.jpg</filename>
		<object>
			<name>helmet</name>
			<ID>0</ID>
			<bndbox>
				<xmin>917</xmin>
				<ymin>546</ymin>
				<xmax>972</xmax>
				<ymax>607</ymax>
			</bndbox>
		</object>
		<object>
			<name>helmet</name>
			<ID>1</ID>
			<bndbox>
				<xmin>465</xmin>
				<ymin>506</ymin>
				<xmax>497</xmax>
				<ymax>544</ymax>
			</bndbox>
		</object>
		<object>
			<name>helmet</name>
			<ID>2</ID>
			<bndbox>
				<xmin>407</xmin>
				<ymin>484</ymin>
				<xmax>425</xmax>
				<ymax>504</ymax>
			</bndbox>
		</object>
		<object>
			<name>two_wheeler</name>
			<ID>2</ID>
			<bndbox>
				<xmin>382</xmin>
				<ymin>484</ymin>
				<xmax>449</xmax>
				<ymax>598</ymax>
			</bndbox>
		</object>
		<object>
			<name>two_wheeler</name>
			<bndbox>
				<xmin>471</xmin>
				<ymin>492</ymin>
				<xmax>541</xmax>
				<ymax>623</ymax>
			</bndbox>
		</object>
		<object>
			<name>two_wheeler</name>
			<ID>0</ID>
			<bndbox>
				<xmin>835</xmin>
				<ymin>548</ymin>
				<xmax>1093</xmax>
				<ymax>908</ymax>
			</bndbox>
		</object>
		<object>
			<name>two_wheeler</name>
			<ID>1</ID>
			<bndbox>
				<xmin>415</xmin>
				<ymin>503</ymin>
				<xmax>541</xmax>
				<ymax>735</ymax>
			</bndbox>
		</object>
	</annotation>