<annotation>
		<filename>0917.jpg</filename>
		<object>
			<name>helmet</name>
			<ID>0</ID>
			<bndbox>
				<xmin>1116</xmin>
				<ymin>588</ymin>
				<xmax>1178</xmax>
				<ymax>655</ymax>
			</bndbox>
		</object>
		<object>
			<name>helmet</name>
			<ID>0</ID>
			<bndbox>
				<xmin>1070</xmin>
				<ymin>573</ymin>
				<xmax>1123</xmax>
				<ymax>637</ymax>
			</bndbox>
		</object>
		<object>
			<name>helmet</name>
			<bndbox>
				<xmin>254</xmin>
				<ymin>521</ymin>
				<xmax>270</xmax>
				<ymax>540</ymax>
			</bndbox>
		</object>
		<object>
			<name>two_wheeler</name>
			<ID>0</ID>
			<bndbox>
				<xmin>1053</xmin>
				<ymin>576</ymin>
				<xmax>1293</xmax>
				<ymax>932</ymax>
			</bndbox>
		</object>
	</annotation>