<annotation>
		<filename>1588.jpg</filename>
		<object>
			<name>helmet</name>
			<ID>0</ID>
			<bndbox>
				<xmin>665</xmin>
				<ymin>546</ymin>
				<xmax>709</xmax>
				<ymax>592</ymax>
			</bndbox>
		</object>
		<object>
			<name>two_wheeler</name>
			<ID>0</ID>
			<bndbox>
				<xmin>637</xmin>
				<ymin>540</ymin>
				<xmax>733</xmax>
				<ymax>709</ymax>
			</bndbox>
		</object>
		<object>
			<name>two_wheeler</name>
			<bndbox>
				<xmin>625</xmin>
				<ymin>551</ymin>
				<xmax>762</xmax>
				<ymax>807</ymax>
			</bndbox>
		</object>
	</annotation>