<annotation>
		<filename>1594.jpg</filename>
		<object>
			<name>helmet</name>
			<ID>0</ID>
			<bndbox>
				<xmin>208</xmin>
				<ymin>534</ymin>
				<xmax>233</xmax>
				<ymax>568</ymax>
			</bndbox>
		</object>
		<object>
			<name>helmet</name>
			<ID>1</ID>
			<bndbox>
				<xmin>358</xmin>
				<ymin>516</ymin>
				<xmax>375</xmax>
				<ymax>534</ymax>
			</bndbox>
		</object>
		<object>
			<name>helmet</name>
			<bndbox>
				<xmin>1207</xmin>
				<ymin>551</ymin>
				<xmax>1233</xmax>
				<ymax>579</ymax>
			</bndbox>
		</object>
		<object>
			<name>two_wheeler</name>
			<bndbox>
				<xmin>207</xmin>
				<ymin>518</ymin>
				<xmax>257</xmax>
				<ymax>619</ymax>
			</bndbox>
		</object>
		<object>
			<name>two_wheeler</name>
			<ID>1</ID>
			<bndbox>
				<xmin>340</xmin>
				<ymin>519</ymin>
				<xmax>394</xmax>
				<ymax>621</ymax>
			</bndbox>
		</object>
		<object>
			<name>two_wheeler</name>
			<ID>0</ID>
			<bndbox>
				<xmin>186</xmin>
				<ymin>534</ymin>
				<xmax>283</xmax>
				<ymax>697</ymax>
			</bndbox>
		</object>
	</annotation>