<annotation>
		<filename>2048.jpg</filename>
		<object>
			<name>helmet</name>
			<ID>0</ID>
			<bndbox>
				<xmin>469</xmin>
				<ymin>559</ymin>
				<xmax>530</xmax>
				<ymax>628</ymax>
			</bndbox>
		</object>
		<object>
			<name>helmet</name>
			<ID>1</ID>
			<bndbox>
				<xmin>976</xmin>
				<ymin>573</ymin>
				<xmax>1044</xmax>
				<ymax>650</ymax>
			</bndbox>
		</object>
		<object>
			<name>helmet</name>
			<ID>1</ID>
			<bndbox>
				<xmin>1059</xmin>
				<ymin>585</ymin>
				<xmax>1125</xmax>
				<ymax>663</ymax>
			</bndbox>
		</object>
		<object>
			<name>helmet</name>
			<ID>3</ID>
			<bndbox>
				<xmin>1624</xmin>
				<ymin>579</ymin>
				<xmax>1702</xmax>
				<ymax>661</ymax>
			</bndbox>
		</object>
		<object>
			<name>helmet</name>
			<ID>3</ID>
			<bndbox>
				<xmin>1685</xmin>
				<ymin>608</ymin>
				<xmax>1787</xmax>
				<ymax>694</ymax>
			</bndbox>
		</object>
		<object>
			<name>two_wheeler</name>
			<ID>3</ID>
			<bndbox>
				<xmin>1547</xmin>
				<ymin>578</ymin>
				<xmax>1920</xmax>
				<ymax>1036</ymax>
			</bndbox>
		</object>
		<object>
			<name>two_wheeler</name>
			<ID>1</ID>
			<bndbox>
				<xmin>946</xmin>
				<ymin>577</ymin>
				<xmax>1338</xmax>
				<ymax>962</ymax>
			</bndbox>
		</object>
		<object>
			<name>two_wheeler</name>
			<ID>0</ID>
			<bndbox>
				<xmin>394</xmin>
				<ymin>562</ymin>
				<xmax>691</xmax>
				<ymax>901</ymax>
			</bndbox>
		</object>
	</annotation>