<annotation>
		<filename>3551.jpg</filename>
		<object>
			<name>helmet</name>
			<ID>0</ID>
			<bndbox>
				<xmin>1818</xmin>
				<ymin>175</ymin>
				<xmax>1833</xmax>
				<ymax>191</ymax>
			</bndbox>
		</object>
		<object>
			<name>helmet</name>
			<ID>0</ID>
			<bndbox>
				<xmin>1831</xmin>
				<ymin>170</ymin>
				<xmax>1843</xmax>
				<ymax>187</ymax>
			</bndbox>
		</object>
		<object>
			<name>two_wheeler</name>
			<ID>0</ID>
			<bndbox>
				<xmin>1799</xmin>
				<ymin>170</ymin>
				<xmax>1860</xmax>
				<ymax>269</ymax>
			</bndbox>
		</object>
	</annotation>