<annotation>
		<filename>3673.jpg</filename>
		<object>
			<name>helmet</name>
			<ID>0</ID>
			<bndbox>
				<xmin>1578</xmin>
				<ymin>336</ymin>
				<xmax>1601</xmax>
				<ymax>362</ymax>
			</bndbox>
		</object>
		<object>
			<name>helmet</name>
			<ID>1</ID>
			<bndbox>
				<xmin>1701</xmin>
				<ymin>321</ymin>
				<xmax>1721</xmax>
				<ymax>341</ymax>
			</bndbox>
		</object>
		<object>
			<name>two_wheeler</name>
			<ID>0</ID>
			<bndbox>
				<xmin>1553</xmin>
				<ymin>335</ymin>
				<xmax>1626</xmax>
				<ymax>468</ymax>
			</bndbox>
		</object>
		<object>
			<name>two_wheeler</name>
			<ID>1</ID>
			<bndbox>
				<xmin>1682</xmin>
				<ymin>315</ymin>
				<xmax>1757</xmax>
				<ymax>420</ymax>
			</bndbox>
		</object>
	</annotation>