<annotation>
		<filename>3982.jpg</filename>
		<object>
			<name>without_helmet</name>
			<ID>0</ID>
			<bndbox>
				<xmin>874</xmin>
				<ymin>404</ymin>
				<xmax>901</xmax>
				<ymax>439</ymax>
			</bndbox>
		</object>
		<object>
			<name>helmet</name>
			<ID>1</ID>
			<bndbox>
				<xmin>1627</xmin>
				<ymin>438</ymin>
				<xmax>1701</xmax>
				<ymax>518</ymax>
			</bndbox>
		</object>
		<object>
			<name>helmet</name>
			<ID>1</ID>
			<bndbox>
				<xmin>1589</xmin>
				<ymin>445</ymin>
				<xmax>1658</xmax>
				<ymax>520</ymax>
			</bndbox>
		</object>
		<object>
			<name>two_wheeler</name>
			<ID>0</ID>
			<bndbox>
				<xmin>842</xmin>
				<ymin>403</ymin>
				<xmax>953</xmax>
				<ymax>556</ymax>
			</bndbox>
		</object>
		<object>
			<name>two_wheeler</name>
			<bndbox>
				<xmin>340</xmin>
				<ymin>397</ymin>
				<xmax>420</xmax>
				<ymax>541</ymax>
			</bndbox>
		</object>
		<object>
			<name>two_wheeler</name>
			<bndbox>
				<xmin>222</xmin>
				<ymin>383</ymin>
				<xmax>283</xmax>
				<ymax>498</ymax>
			</bndbox>
		</object>
		<object>
			<name>two_wheeler</name>
			<ID>1</ID>
			<bndbox>
				<xmin>1418</xmin>
				<ymin>438</ymin>
				<xmax>1757</xmax>
				<ymax>844</ymax>
			</bndbox>
		</object>
	</annotation>