<annotation>
		<filename>4487.jpg</filename>
		<object>
			<name>helmet</name>
			<ID>0</ID>
			<bndbox>
				<xmin>1066</xmin>
				<ymin>652</ymin>
				<xmax>1102</xmax>
				<ymax>688</ymax>
			</bndbox>
		</object>
		<object>
			<name>without_helmet</name>
			<ID>1</ID>
			<bndbox>
				<xmin>545</xmin>
				<ymin>709</ymin>
				<xmax>578</xmax>
				<ymax>754</ymax>
			</bndbox>
		</object>
		<object>
			<name>two_wheeler</name>
			<ID>1</ID>
			<bndbox>
				<xmin>501</xmin>
				<ymin>706</ymin>
				<xmax>661</xmax>
				<ymax>975</ymax>
			</bndbox>
		</object>
		<object>
			<name>two_wheeler</name>
			<ID>0</ID>
			<bndbox>
				<xmin>1014</xmin>
				<ymin>650</ymin>
				<xmax>1160</xmax>
				<ymax>853</ymax>
			</bndbox>
		</object>
	</annotation>